hausa/__init__.py
hwn/__init__.py
hwn/kamus.json
hwn-0.1.0.data/data/kamus.json
hwn-0.1.0.data/scripts/__init__.py
hwn-0.1.0.data/scripts/hwn
hwn-0.1.0.dist-info/METADATA
hwn-0.1.0.dist-info/WHEEL
hwn-0.1.0.dist-info/top_level.txt
hwn-0.1.0.dist-info/RECORD
