Metadata-Version: 2.1
Name: hwn
Version: 0.1.0
Summary: A hausa wordnet library
Home-page: https://github.com/meenah-imam/hwn
Author: Amina Imam Abubakar
Author-email: aminaimamabubakar@gmail.com
License: UNKNOWN
Platform: UNKNOWN
Classifier: Programming Language :: Python :: 3
Classifier: License :: OSI Approved :: MIT License
Classifier: Operating System :: OS Independent
